{
    "song_details": [
        {
            "song_id": 1,
            "song_title": "Viva La Vida",
            "song_artist": "Coldplay",
            "spotify_link": [
                {
                    "song_link": "https://open.spotify.com/intl-es/track/1mea3bSkSGXuIRvnydlB5b"
                }
            ]
        },
        {
            "song_id": 2,
            "song_title": "The Scientist",
            "song_artist": "Coldplay",
            "spotify_link": [
                {
                    "song_link": "https://open.spotify.com/track/75JFxkI2RXiU7L9VXzMkle"
                }
            ]
        },
        {
            "song_id": 3,
            "song_title": "Yellow",
            "song_artist": "Coldplay",
            "spotify_link": [
                {
                    "song_link": "https://open.spotify.com/track/3AJwUDP919kvQ9QcozQPxg"
                }
            ]
        },
        {
            "song_id": 4,
            "song_title": "Fix You",
            "song_artist": "Coldplay",
            "spotify_link": [
                {
                    "song_link": "https://open.spotify.com/intl-es/track/4cr1WGEgAucOtYEq2wrwlV"
                }
            ]
        },
        {
            "song_id": 5,
            "song_title": "Hymn for the Weekend",
            "song_artist": "Coldplay",
            "spotify_link": [
                {
                    "song_link": "https://open.spotify.com/track/3RiPr603aXAoi4GHyXx0uy"
                }
            ]
        },
        {
            "song_id": 6,
            "song_title": "Creep",
            "song_artist": "Radiohead",
            "spotify_link": [
                {
                    "song_link": "https://open.spotify.com/track/70LcF31zb1H0PyJoS1Sx1r"
                }
            ]
        },
        {
            "song_id": 7,
            "song_title": "Karma Police",
            "song_artist": "Radiohead",
            "spotify_link": [
                {
                    "song_link": "https://open.spotify.com/track/63OQupATfueTdZMWTxW03A"
                }
            ]
        },
        {
            "song_id": 8,
            "song_title": "No Surprises",
            "song_artist": "Radiohead",
            "spotify_link": [
                {
                    "song_link": "https://open.spotify.com/track/10nyNJ6zNy2YVYLrcwLccB"
                }
            ]
        },
        {
            "song_id": 9,
            "song_title": "Exit Music (For A Film)",
            "song_artist": "Radiohead",
            "spotify_link": [
                {
                    "song_link": "https://open.spotify.com/track/0z1o5L7HJx562xZSATcIpY"
                }
            ]
        },
        {
            "song_id": 10,
            "song_title": "Paranoid Android",
            "song_artist": "Radiohead",
            "spotify_link": [
                {
                    "song_link": "https://open.spotify.com/track/6LgJvl0Xdtc73RJ1mmpotq"
                }
            ]
        },
        {
            "song_id": 11,
            "song_title": "Californication",
            "song_artist": "Red Hot Chili Peppers",
            "spotify_link": [
                {
                    "song_link": "https://open.spotify.com/track/48UPSzbZjgc449aqz8bxox"
                }
            ]
        },
        {
            "song_id": 12,
            "song_title": "Under the Bridge",
            "song_artist": "Red Hot Chili Peppers",
            "spotify_link": [
                {
                    "song_link": "https://open.spotify.com/track/3d9DChrdc6BOeFsbrZ3Is0"
                }
            ]
        },
        {
            "song_id": 13,
            "song_title": "Can’t Stop",
            "song_artist": "Red Hot Chili Peppers",
            "spotify_link": [
                {
                    "song_link": "https://open.spotify.com/track/4BcS4LomxUnQpzx4hCaJTs"
                }
            ]
        },
        {
            "song_id": 14,
            "song_title": "Otherside",
            "song_artist": "Red Hot Chili Peppers",
            "spotify_link": [
                {
                    "song_link": "https://open.spotify.com/track/64BbK9SFKH2jk86U3dGj2P"
                }
            ]
        },
        {
            "song_id": 15,
            "song_title": "Scar Tissue",
            "song_artist": "Red Hot Chili Peppers",
            "spotify_link": [
                {
                    "song_link": "https://open.spotify.com/track/1G391cbiT3v3Cywg8T7DM1"
                }
            ]
        },
        {
            "song_id": 16,
            "song_title": "Work",
            "song_artist": "Rihanna",
            "spotify_link": [
                {
                    "song_link": "https://open.spotify.com/track/72TFWvU3wUYdUuxejTTIzt"
                }
            ]
        },
        {
            "song_id": 17,
            "song_title": "Love on the Brain",
            "song_artist": "Rihanna",
            "spotify_link": [
                {
                    "song_link": "https://open.spotify.com/track/5oO3drDxtziYU2H1X23ZIp"
                }
            ]
        },
        {
            "song_id": 18,
            "song_title": "Needed Me",
            "song_artist": "Rihanna",
            "spotify_link": [
                {
                    "song_link": "https://open.spotify.com/track/4pAl7FkDMNBsjykPXo91B3"
                }
            ]
        },
        {
            "song_id": 19,
            "song_title": "Stay",
            "song_artist": "Rihanna",
            "spotify_link": [
                {
                    "song_link": "https://open.spotify.com/track/1dEy9Pl81QopSxNsPxXQxv"
                }
            ]
        },
        {
            "song_id": 20,
            "song_title": "FourFiveSeconds",
            "song_artist": "Rihanna",
            "spotify_link": [
                {
                    "song_link": "https://open.spotify.com/track/78TTtXnFQPzwqlbtbwqN0y"
                }
            ]
        },
        {
            "song_id": 21,
            "song_title": "Rap God",
            "song_artist": "Eminem",
            "spotify_link": [
                {
                    "song_link": "https://open.spotify.com/track/6or1bKJiZ06IlK0vFvY75k"
                }
            ]
        },
        {
            "song_id": 22,
            "song_title": "Lose Yourself",
            "song_artist": "Eminem",
            "spotify_link": [
                {
                    "song_link": "https://open.spotify.com/track/7MJQ9Nfxzh8LPZ9e9u68Fq"
                }
            ]
        },
        {
            "song_id": 23,
            "song_title": "Mockingbird",
            "song_artist": "Eminem",
            "spotify_link": [
                {
                    "song_link": "https://open.spotify.com/track/561jH07mF1jHuk7KlaeF0s"
                }
            ]
        },
        {
            "song_id": 24,
            "song_title": "Without Me",
            "song_artist": "Eminem",
            "spotify_link": [
                {
                    "song_link": "https://open.spotify.com/track/7lQ8MOhq6IN2w8EYcFNSUk"
                }
            ]
        },
        {
            "song_id": 25,
            "song_title": "The Real Slim Shady",
            "song_artist": "Eminem",
            "spotify_link": [
                {
                    "song_link": "https://open.spotify.com/track/3yfqSUWxFvZELEM4PmlwIR"
                }
            ]
        },
        {
            "song_id": 26,
            "song_title": "Mr. Brightside",
            "song_artist": "The Killers",
            "spotify_link": [
                {
                    "song_link": "https://open.spotify.com/track/003vvx7Niy0yvhvHt4a68B"
                }
            ]
        },
        {
            "song_id": 27,
            "song_title": "All These Things That I’ve Done",
            "song_artist": "The Killers",
            "spotify_link": [
                {
                    "song_link": "https://open.spotify.com/track/0kYUrLVQOfx21xuXu7OGrT"
                }
            ]
        },
        {
            "song_id": 28,
            "song_title": "Somebody Told Me",
            "song_artist": "The Killers",
            "spotify_link": [
                {
                    "song_link": "https://open.spotify.com/track/6PwjJ58I4t7Mae9xfZ9l9v"
                }
            ]
        },
        {
            "song_id": 29,
            "song_title": "Human",
            "song_artist": "The Killers",
            "spotify_link": [
                {
                    "song_link": "https://open.spotify.com/track/1sTsuZTdANkiFd7T34H3nb"
                }
            ]
        },
        {
            "song_id": 30,
            "song_title": "When You Were Young",
            "song_artist": "The Killers",
            "spotify_link": [
                {
                    "song_link": "https://open.spotify.com/track/70wYA8oYHoMzhRRkARoMhU"
                }
            ]
        },
        {
            "song_id": 31,
            "song_title": "Mercy",
            "song_artist": "Kanye West",
            "spotify_link": [
                {
                    "song_link": "https://open.spotify.com/track/4qikXelSRKvoCqFcHLB2H2"
                }
            ]
        },
        {
            "song_id": 32,
            "song_title": "Monster",
            "song_artist": "Kanye West",
            "spotify_link": [
                {
                    "song_link": "https://open.spotify.com/track/1ZHYJ2Wwgxes4m8Ba88PeK"
                }
            ]
        },
        {
            "song_id": 33,
            "song_title": "Father Stretch My Hands Pt. 1",
            "song_artist": "Kanye West",
            "spotify_link": [
                {
                    "song_link": "https://open.spotify.com/track/4KW1lqgSr8TKrvBII0Brf8"
                }
            ]
        },
        {
            "song_id": 34,
            "song_title": "Ultralight Beam",
            "song_artist": "Kanye West",
            "spotify_link": [
                {
                    "song_link": "https://open.spotify.com/track/1eQBEelI2NCy7AUTerX0KS"
                }
            ]
        },
        {
            "song_id": 35,
            "song_title": "Bound 2",
            "song_artist": "Kanye West",
            "spotify_link": [
                {
                    "song_link": "https://open.spotify.com/track/3sNVsP50132BTNlImLx70i"
                }
            ]
        },
        {
            "song_id": 36,
            "song_title": "Smells Like Teen Spirit",
            "song_artist": "Nirvana",
            "spotify_link": [
                {
                    "song_link": "https://open.spotify.com/track/5ghIJDpPoe3CfHMGu71E6T"
                }
            ]
        },
        {
            "song_id": 37,
            "song_title": "Come as You Are",
            "song_artist": "Nirvana",
            "spotify_link": [
                {
                    "song_link": "https://open.spotify.com/track/4P5KoWXOxwuobLmHXLMobV"
                }
            ]
        },
        {
            "song_id": 38,
            "song_title": "Heart-Shaped Box",
            "song_artist": "Nirvana",
            "spotify_link": [
                {
                    "song_link": "https://open.spotify.com/track/11LmqTE2naFULdEP94AUBa"
                }
            ]
        },
        {
            "song_id": 39,
            "song_title": "Lithium",
            "song_artist": "Nirvana",
            "spotify_link": [
                {
                    "song_link": "https://open.spotify.com/intl-es/track/2YodwKJnbPyNKe8XXSE9V7"
                }
            ]
        },
        {
            "song_id": 40,
            "song_title": "Drain You",
            "song_artist": "Nirvana",
            "spotify_link": [
                {
                    "song_link": "https://open.spotify.com/track/5Ddlk6C2JVxb1SReZ6O1wk"
                }
            ]
        },
        {
            "song_id": 41,
            "song_title": "Uprising",
            "song_artist": "Muse",
            "spotify_link": [
                {
                    "song_link": "https://open.spotify.com/track/4VqPOruhp5EdPBeR92t6lQ"
                }
            ]
        },
        {
            "song_id": 42,
            "song_title": "Supermassive Black Hole",
            "song_artist": "Muse",
            "spotify_link": [
                {
                    "song_link": "https://open.spotify.com/track/3lPr8ghNDBLc2uZovNyLs9"
                }
            ]
        },
        {
            "song_id": 43,
            "song_title": "Time Is Running Out",
            "song_artist": "Muse",
            "spotify_link": [
                {
                    "song_link": "https://open.spotify.com/track/2takcwOaAZWiXQijPHIx7B"
                }
            ]
        },
        {
            "song_id": 44,
            "song_title": "Starlight",
            "song_artist": "Muse",
            "spotify_link": [
                {
                    "song_link": "https://open.spotify.com/track/3skn2lauGk7Dx6bVIt5DVj"
                }
            ]
        },
        {
            "song_id": 45,
            "song_title": "Hysteria",
            "song_artist": "Muse",
            "spotify_link": [
                {
                    "song_link": "https://open.spotify.com/track/7xyYsOvq5Ec3P4fr6mM9fD"
                }
            ]
        },
        {
            "song_id": 46,
            "song_title": "Bohemian Rhapsody",
            "song_artist": "Queen",
            "spotify_link": [
                {
                    "song_link": "https://open.spotify.com/track/6l8GvAyoUZwWDgF1e4822w"
                }
            ]
        },
        {
            "song_id": 47,
            "song_title": "Don’t Stop Me Now",
            "song_artist": "Queen",
            "spotify_link": [
                {
                    "song_link": "https://open.spotify.com/track/2jNCofCae2Txs2zaegNLOt"
                }
            ]
        },
        {
            "song_id": 48,
            "song_title": "Under Pressure",
            "song_artist": "Queen",
            "spotify_link": [
                {
                    "song_link": "https://open.spotify.com/track/2fuCquhmrzHpu5xcA1ci9x"
                }
            ]
        },
        {
            "song_id": 49,
            "song_title": "Killer Queen",
            "song_artist": "Queen",
            "spotify_link": [
                {
                    "song_link": "https://open.spotify.com/track/70wvmV1Dyg1xWtCYSngm4R"
                }
            ]
        },
        {
            "song_id": 50,
            "song_title": "Love of My Life",
            "song_artist": "Queen",
            "spotify_link": [
                {
                    "song_link": "https://open.spotify.com/track/5C6D9gICTE0rS0xfF2udY8"
                }
            ]
        },
        {
            "song_id": 51,
            "song_title": "Everlong",
            "song_artist": "Foo Fighters",
            "spotify_link": [
                {
                    "song_link": "https://open.spotify.com/track/5UWwZ5lm5PKu6eKsHAGxOk"
                }
            ]
        },
        {
            "song_id": 52,
            "song_title": "My Hero",
            "song_artist": "Foo Fighters",
            "spotify_link": [
                {
                    "song_link": "https://open.spotify.com/track/7u5dBtASrtOuBTTZjJrvuJ"
                }
            ]
        },
        {
            "song_id": 53,
            "song_title": "The Pretender",
            "song_artist": "Foo Fighters",
            "spotify_link": [
                {
                    "song_link": "https://open.spotify.com/track/7x8dCjCr0x6x2lXKujYD34"
                }
            ]
        },
        {
            "song_id": 54,
            "song_title": "All My Life",
            "song_artist": "Foo Fighters",
            "spotify_link": [
                {
                    "song_link": "https://open.spotify.com/track/6tsojOQ5wHaIjKqIryLZK6"
                }
            ]
        },
        {
            "song_id": 55,
            "song_title": "Best of You",
            "song_artist": "Foo Fighters",
            "spotify_link": [
                {
                    "song_link": "https://open.spotify.com/track/5FZxsHWIvUsmSK1IAvm2pp"
                }
            ]
        },
        {
            "song_id": 56,
            "song_title": "In the End",
            "song_artist": "Linkin Park",
            "spotify_link": [
                {
                    "song_link": "https://open.spotify.com/track/1Yu3HeEnhuzD5rmoiJNv1N"
                }
            ]
        },
        {
            "song_id": 57,
            "song_title": "Numb",
            "song_artist": "Linkin Park",
            "spotify_link": [
                {
                    "song_link": "https://open.spotify.com/track/2nLtzopw4rPReszdYBJU6h"
                }
            ]
        },
        {
            "song_id": 58,
            "song_title": "One More Light",
            "song_artist": "Linkin Park",
            "spotify_link": [
                {
                    "song_link": "https://open.spotify.com/track/3xXBsjrbG1xQIm1xv1cKOt"
                }
            ]
        },
        {
            "song_id": 59,
            "song_title": "Heavy",
            "song_artist": "Linkin Park",
            "spotify_link": [
                {
                    "song_link": "https://open.spotify.com/track/61omx7Yj1LwtGx1Ad8nZXT"
                }
            ]
        },
        {
            "song_id": 60,
            "song_title": "The Emptiness Machine",
            "song_artist": "Linkin Park",
            "spotify_link": [
                {
                    "song_link": "https://open.spotify.com/track/2PnlsTsOTLE5jnBnNe2K0A"
                }
            ]
        },
        {
            "song_id": 61,
            "song_title": "Shallow",
            "song_artist": "Lady Gaga",
            "spotify_link": [
                {
                    "song_link": "https://open.spotify.com/track/2VxeLyX666F8uXCJ0dZF8B"
                }
            ]
        },
        {
            "song_id": 62,
            "song_title": "Die With A Smile",
            "song_artist": "Lady Gaga",
            "spotify_link": [
                {
                    "song_link": "https://open.spotify.com/track/2plbrEY59IikOBgBGLjaoe"
                }
            ]
        },
        {
            "song_id": 63,
            "song_title": "Poker Face",
            "song_artist": "Lady Gaga",
            "spotify_link": [
                {
                    "song_link": "https://open.spotify.com/track/1QV6tiMFM6fSOKOGLMHYYg"
                }
            ]
        },
        {
            "song_id": 64,
            "song_title": "Bad Romance",
            "song_artist": "Lady Gaga",
            "spotify_link": [
                {
                    "song_link": "https://open.spotify.com/track/0SiywuOBRcynK0uKGWdCnn"
                }
            ]
        },
        {
            "song_id": 65,
            "song_title": "Abracadabra",
            "song_artist": "Lady Gaga",
            "spotify_link": [
                {
                    "song_link": "https://open.spotify.com/track/5ZLUm9eab8y3tqQ1OhQSHI"
                }
            ]
        },
        {
            "song_id": 66,
            "song_title": "Sympathy for the Devil",
            "song_artist": "The Rolling Stones",
            "spotify_link": [
                {
                    "song_link": "https://open.spotify.com/track/75zMKn5euxQdlkZgu4P42J"
                }
            ]
        },
        {
            "song_id": 67,
            "song_title": "Paint It, Black",
            "song_artist": "The Rolling Stones",
            "spotify_link": [
                {
                    "song_link": "https://open.spotify.com/track/63T7DJ1AFDD6Bn8VzG6JE8"
                }
            ]
        },
        {
            "song_id": 68,
            "song_title": "Brown Sugar",
            "song_artist": "The Rolling Stones",
            "spotify_link": [
                {
                    "song_link": "https://open.spotify.com/track/61UuPxxYUvacEH6SHIK3sU"
                }
            ]
        },
        {
            "song_id": 69,
            "song_title": "Gimme Shelter",
            "song_artist": "The Rolling Stones",
            "spotify_link": [
                {
                    "song_link": "https://open.spotify.com/track/1dv3ePjze9tPq2pk8eWJdR"
                }
            ]
        },
        {
            "song_id": 70,
            "song_title": "Wild Horses",
            "song_artist": "The Rolling Stones",
            "spotify_link": [
                {
                    "song_link": "https://open.spotify.com/track/4M4Q3JLsUbyTkd5WHty1WB"
                }
            ]
        },
        {
            "song_id": 71,
            "song_title": "Get Lucky",
            "song_artist": "Daft Punk",
            "spotify_link": [
                {
                    "song_link": "https://open.spotify.com/track/69kOkLUCkxIZYexIgSG8rq"
                }
            ]
        },
        {
            "song_id": 72,
            "song_title": "Instant Crush",
            "song_artist": "Daft Punk",
            "spotify_link": [
                {
                    "song_link": "https://open.spotify.com/track/2cGxRwrMyEAp8dEbuZaVv6"
                }
            ]
        },
        {
            "song_id": 73,
            "song_title": "Touch",
            "song_artist": "Daft Punk",
            "spotify_link": [
                {
                    "song_link": "https://open.spotify.com/track/7oaEjLP2dTJLJsITbAxTOz"
                }
            ]
        },
        {
            "song_id": 74,
            "song_title": "Giorgio by Moroder",
            "song_artist": "Daft Punk",
            "spotify_link": [
                {
                    "song_link": "https://open.spotify.com/track/0oks4FnzhNp5QPTZtoet7c"
                }
            ]
        },
        {
            "song_id": 75,
            "song_title": "Lose Yourself to Dance",
            "song_artist": "Daft Punk",
            "spotify_link": [
                {
                    "song_link": "https://open.spotify.com/track/5CMjjywI0eZMixPeqNd75R"
                }
            ]
        },
        {
            "song_id": 76,
            "song_title": "Boulevard of Broken Dreams",
            "song_artist": "Green Day",
            "spotify_link": [
                {
                    "song_link": "https://open.spotify.com/album/2sIWM1FzNqLCccNwXuC4SA"
                }
            ]
        },
        {
            "song_id": 77,
            "song_title": "American Idiot",
            "song_artist": "Green Day",
            "spotify_link": [
                {
                    "song_link": "https://open.spotify.com/track/6nTiIhLmQ3FWhvrGafw2zj"
                }
            ]
        },
        {
            "song_id": 78,
            "song_title": "Holiday",
            "song_artist": "Green Day",
            "spotify_link": [
                {
                    "song_link": "https://open.spotify.com/track/4VgEM12OeaN3GyBV487Me7"
                }
            ]
        },
        {
            "song_id": 79,
            "song_title": "Good Riddance (Time of Your Life)",
            "song_artist": "Green Day",
            "spotify_link": [
                {
                    "song_link": "https://open.spotify.com/track/6ORqU0bHbVCRjXm9AjyHyZ"
                }
            ]
        },
        {
            "song_id": 80,
            "song_title": "Basket Case",
            "song_artist": "Green Day",
            "spotify_link": [
                {
                    "song_link": "https://open.spotify.com/track/6L89mwZXSOwYl76YXfX13s"
                }
            ]
        },
        {
            "song_id": 81,
            "song_title": "Swish Swish",
            "song_artist": "Katy Perry",
            "spotify_link": [
                {
                    "song_link": "https://open.spotify.com/track/4jgvPFeCE4V2HkYX6luV9B"
                }
            ]
        },
        {
            "song_id": 82,
            "song_title": "California Gurls",
            "song_artist": "Katy Perry",
            "spotify_link": [
                {
                    "song_link": "https://open.spotify.com/album/58WjN295lBQlajYL241P6Y"
                }
            ]
        },
        {
            "song_id": 83,
            "song_title": "Dark Horse",
            "song_artist": "Katy Perry",
            "spotify_link": [
                {
                    "song_link": "https://open.spotify.com/track/4jbmgIyjGoXjY01XxatOx6"
                }
            ]
        },
        {
            "song_id": 84,
            "song_title": "Chained To The Rhythm",
            "song_artist": "Katy Perry",
            "spotify_link": [
                {
                    "song_link": "https://open.spotify.com/track/0eME2QCeBseI7Qt7IwG3Vw"
                }
            ]
        },
        {
            "song_id": 85,
            "song_title": "The One That Got Away",
            "song_artist": "Katy Perry",
            "spotify_link": [
                {
                    "song_link": "https://open.spotify.com/track/3oL3XRtkP1WVbMxf7dtTdu"
                }
            ]
        },
        {
            "song_id": 86,
            "song_title": "Yesterday",
            "song_artist": "The Beatles",
            "spotify_link": []
        },
        {
            "song_id": 87,
            "song_title": "In My Life",
            "song_artist": "The Beatles",
            "spotify_link": [
                {
                    "song_link": "https://open.spotify.com/track/6dZ2ygZLxaPHnDuOHYQHAM"
                }
            ]
        },
        {
            "song_id": 88,
            "song_title": "Let It Be",
            "song_artist": "The Beatles",
            "spotify_link": [
                {
                    "song_link": "https://open.spotify.com/track/7iN1s7xHE4ifF5povM6A48"
                }
            ]
        },
        {
            "song_id": 89,
            "song_title": "Hey Jude",
            "song_artist": "The Beatles",
            "spotify_link": [
                {
                    "song_link": "https://open.spotify.com/track/0aym2LBJBk9DAYuHHutrIl"
                }
            ]
        },
        {
            "song_id": 90,
            "song_title": "Come Together",
            "song_artist": "The Beatles",
            "spotify_link": [
                {
                    "song_link": "https://open.spotify.com/track/2EqlS6tkEnglzr7tkKAAYD"
                }
            ]
        },
        {
            "song_id": 91,
            "song_title": "Don’t Look Back in Anger",
            "song_artist": "Oasis",
            "spotify_link": []
        },
        {
            "song_id": 92,
            "song_title": "Wonderwall",
            "song_artist": "Oasis",
            "spotify_link": [
                {
                    "song_link": "https://open.spotify.com/track/1qPbGZqppFwLwcBC1JQ6Vr"
                }
            ]
        },
        {
            "song_id": 93,
            "song_title": "Stand by Me",
            "song_artist": "Oasis",
            "spotify_link": []
        },
        {
            "song_id": 94,
            "song_title": "Champagne Supernova",
            "song_artist": "Oasis",
            "spotify_link": [
                {
                    "song_link": "https://open.spotify.com/track/6EMynpZ10GVcwVqiLZj6Ye"
                }
            ]
        },
        {
            "song_id": 95,
            "song_title": "Supersonic",
            "song_artist": "Oasis",
            "spotify_link": [
                {
                    "song_link": "https://open.spotify.com/track/4jJfa4mO5JjV9Tz2aAxE2M"
                }
            ]
        },
        {
            "song_id": 96,
            "song_title": "Feel Good Inc.",
            "song_artist": "Gorillaz",
            "spotify_link": [
                {
                    "song_link": "https://open.spotify.com/track/0d28khcov6AiegSCpG5TuT"
                }
            ]
        },
        {
            "song_id": 97,
            "song_title": "Clint Eastwood",
            "song_artist": "Gorillaz",
            "spotify_link": [
                {
                    "song_link": "https://open.spotify.com/track/7yMiX7n9SBvadzox8T5jzT"
                }
            ]
        },
        {
            "song_id": 98,
            "song_title": "Saturnz Barz",
            "song_artist": "Gorillaz",
            "spotify_link": [
                {
                    "song_link": "https://open.spotify.com/track/2oJInAFXiQYLgz0jh9MrXf"
                }
            ]
        },
        {
            "song_id": 99,
            "song_title": "On Melancholy Hill",
            "song_artist": "Gorillaz",
            "spotify_link": [
                {
                    "song_link": "https://open.spotify.com/track/0q6LuUqGLUiCPP1cbdwFs3"
                }
            ]
        },
        {
            "song_id": 100,
            "song_title": "Rhinestone Eyes",
            "song_artist": "Gorillaz",
            "spotify_link": [
                {
                    "song_link": "https://open.spotify.com/track/1foMv2HQwfQ2vntFf9HFeG"
                }
            ]
        }
    ]
}